{
  "users": [
    {
      "id": 20,
      "title": "collaborative",
      "description": "Ergonomic executive chair upholstered in bonded black leather and PVC padded seat and back for all-day comfort and support",
      "price": "€191",
      "picture": "http://placeimg.com/640/480/sports",
      "street": "946 Amiel Molière",
      "city": "Maillardland",
      "country": "Corée du Sud",
      "joining_date": "2020-01-10T23:08:43.926Z"
    },
    {
      "id": 19,
      "title": "sticky",
      "description": "The automobile layout consists of a front-engine design, with transaxle-type transmissions mounted at the rear of the engine and four wheel drive",
      "price": "€163",
      "picture": "http://placeimg.com/640/480/sports",
      "street": "22567 Fanny Vaneau",
      "city": "Éliastad",
      "country": "Mali",
      "joining_date": "2020-01-28T07:38:05.745Z"
    },
    {
      "id": 18,
      "title": "best-of-breed",
      "description": "New ABC 13 9370, 13.3, 5th Gen CoreA5-8250U, 8GB RAM, 256GB SSD, power UHD Graphics, OS 10 Home, OS Office A & J 2016",
      "price": "€158",
      "picture": "http://placeimg.com/640/480/sports",
      "street": "24793 Cousin de Rivoli",
      "city": "Anstrudieshire",
      "country": "Cap-Vert",
      "joining_date": "2020-01-12T13:16:34.533Z"
    },
    {
      "id": 17,
      "title": "best-of-breed",
      "description": "Ergonomic executive chair upholstered in bonded black leather and PVC padded seat and back for all-day comfort and support",
      "price": "€140",
      "picture": "http://placeimg.com/640/480/sports",
      "street": "93595 Denis de Nesle",
      "city": "Thibaultport",
      "country": "Suriname",
      "joining_date": "2020-01-11T04:04:46.398Z"
    },
    {
      "id": 16,
      "title": "distributed",
      "description": "Boston's most advanced compression wear technology increases muscle oxygenation, stabilizes active muscles",
      "price": "€162",
      "picture": "http://placeimg.com/640/480/sports",
      "street": "64991 Sophie Saint-Honoré",
      "city": "Lake Lucienneview",
      "country": "Madagascar",
      "joining_date": "2020-01-27T17:00:03.321Z"
    },
    {
      "id": 15,
      "title": "visionary",
      "description": "Andy shoes are designed to keeping in mind durability as well as trends, the most stylish range of shoes & sandals",
      "price": "€165",
      "picture": "http://placeimg.com/640/480/sports",
      "street": "491 Dubois de l'Odéon",
      "city": "Huberttown",
      "country": "Koweït",
      "joining_date": "2020-01-30T13:03:57.532Z"
    },
    {
      "id": 14,
      "title": "holistic",
      "description": "The automobile layout consists of a front-engine design, with transaxle-type transmissions mounted at the rear of the engine and four wheel drive",
      "price": "€157",
      "picture": "http://placeimg.com/640/480/sports",
      "street": "5924 Antonine Mouffetard",
      "city": "Lake Ambre",
      "country": "Côte d’Ivoire",
      "joining_date": "2020-01-23T15:32:13.277Z"
    },
    {
      "id": 13,
      "title": "cross-media",
      "description": "New ABC 13 9370, 13.3, 5th Gen CoreA5-8250U, 8GB RAM, 256GB SSD, power UHD Graphics, OS 10 Home, OS Office A & J 2016",
      "price": "€102",
      "picture": "http://placeimg.com/640/480/sports",
      "street": "65275 Japhet de l'Odéon",
      "city": "Petitview",
      "country": "Népal",
      "joining_date": "2020-01-18T21:24:22.046Z"
    },
    {
      "id": 12,
      "title": "cutting-edge",
      "description": "The Nagasaki Lander is the trademarked name of several series of Nagasaki sport bikes, that started with the 1984 ABC800J",
      "price": "€124",
      "picture": "http://placeimg.com/640/480/sports",
      "street": "347 Althée Laffitte",
      "city": "North Pierre",
      "country": "Libye",
      "joining_date": "2020-01-16T12:38:57.666Z"
    },
    {
      "id": 11,
      "title": "one-to-one",
      "description": "Ergonomic executive chair upholstered in bonded black leather and PVC padded seat and back for all-day comfort and support",
      "price": "€165",
      "picture": "http://placeimg.com/640/480/sports",
      "street": "295 Maillard de Tilsitt",
      "city": "North Arnaudfort",
      "country": "République dominicaine",
      "joining_date": "2020-01-28T22:19:42.621Z"
    },
    {
      "id": 10,
      "title": "virtual",
      "description": "Ergonomic executive chair upholstered in bonded black leather and PVC padded seat and back for all-day comfort and support",
      "price": "€175",
      "picture": "http://placeimg.com/640/480/sports",
      "street": "7038 Eudes Delesseux",
      "city": "East Aurélienne",
      "country": "Pérou",
      "joining_date": "2020-01-16T10:16:36.924Z"
    },
    {
      "id": 9,
      "title": "leading-edge",
      "description": "Boston's most advanced compression wear technology increases muscle oxygenation, stabilizes active muscles",
      "price": "€133",
      "picture": "http://placeimg.com/640/480/sports",
      "street": "21413 Rey du Havre",
      "city": "Benoîtfort",
      "country": "Haïti",
      "joining_date": "2020-01-30T04:04:08.973Z"
    },
    {
      "id": 8,
      "title": "e-business",
      "description": "The beautiful range of Apple Naturalé that has an exciting mix of natural ingredients. With the Goodness of 100% Natural Ingredients",
      "price": "€164",
      "picture": "http://placeimg.com/640/480/sports",
      "street": "8939 Georgette de la Huchette",
      "city": "Lake Nicolasmouth",
      "country": "Tunisie",
      "joining_date": "2020-01-03T16:28:06.084Z"
    },
    {
      "id": 7,
      "title": "cutting-edge",
      "description": "New range of formal shirts are designed keeping you in mind. With fits and styling that will make you stand apart",
      "price": "€102",
      "picture": "http://placeimg.com/640/480/sports",
      "street": "9731 Maillard d'Abbeville",
      "city": "Garciaborough",
      "country": "Mauritanie",
      "joining_date": "2020-01-03T23:25:36.770Z"
    },
    {
      "id": 6,
      "title": "one-to-one",
      "description": "New range of formal shirts are designed keeping you in mind. With fits and styling that will make you stand apart",
      "price": "€192",
      "picture": "http://placeimg.com/640/480/sports",
      "street": "631 Paris d'Abbeville",
      "city": "Royertown",
      "country": "Indonésie",
      "joining_date": "2020-01-27T08:42:52.276Z"
    },
    {
      "id": 5,
      "title": "B2B",
      "description": "Boston's most advanced compression wear technology increases muscle oxygenation, stabilizes active muscles",
      "price": "€191",
      "picture": "http://placeimg.com/640/480/sports",
      "street": "1295 Olivier de l'Odéon",
      "city": "West Adrienne",
      "country": "Bhoutan",
      "joining_date": "2020-01-08T00:23:30.375Z"
    },
    {
      "id": 4,
      "title": "frictionless",
      "description": "The beautiful range of Apple Naturalé that has an exciting mix of natural ingredients. With the Goodness of 100% Natural Ingredients",
      "price": "€131",
      "picture": "http://placeimg.com/640/480/sports",
      "street": "6104 Faure Dauphine",
      "city": "Nancy",
      "country": "Dominique",
      "joining_date": "2020-01-19T22:48:51.735Z"
    },
    {
      "id": 3,
      "title": "real-time",
      "description": "The Nagasaki Lander is the trademarked name of several series of Nagasaki sport bikes, that started with the 1984 ABC800J",
      "price": "€170",
      "picture": "http://placeimg.com/640/480/sports",
      "street": "5751 Philothée Adolphe Mille",
      "city": "Lille",
      "country": "Antigua-et-Barbuda",
      "joining_date": "2020-01-06T16:01:53.015Z"
    },
    {
      "id": 2,
      "title": "24/365",
      "description": "New range of formal shirts are designed keeping you in mind. With fits and styling that will make you stand apart",
      "price": "€118",
      "picture": "http://placeimg.com/640/480/sports",
      "street": "66397 Suzon de la Huchette",
      "city": "Dijon",
      "country": "Saint-Christophe-et-Niévès",
      "joining_date": "2020-01-25T14:39:29.017Z"
    },
    {
      "id": 1,
      "title": "next-generation",
      "description": "Carbonite web goalkeeper gloves are ergonomically designed to give easy fit",
      "price": "€127",
      "picture": "http://placeimg.com/640/480/sports",
      "street": "49947 Legrand de Solférino",
      "city": "Palémonchester",
      "country": "Bénin",
      "joining_date": "2020-01-01T00:36:29.900Z"
    },
    {
      "id": 0,
      "title": "efficient",
      "description": "Andy shoes are designed to keeping in mind durability as well as trends, the most stylish range of shoes & sandals",
      "price": "€104",
      "picture": "http://placeimg.com/640/480/sports",
      "street": "46353 Leroy de Rivoli",
      "city": "East Sandra",
      "country": "Suède",
      "joining_date": "2020-01-07T21:48:22.414Z"
    }
  ]
}
